MANIFEST.in
Makefile
README.rst
setup.py
discussions/__init__.py
discussions/compat.py
discussions/fields.py
discussions/helpers.py
discussions/managers.py
discussions/settings.py
discussions/urls.py
discussions/utils.py
discussions/forms/__init__.py
discussions/forms/base.py
discussions/models/__init__.py
discussions/models/base.py
discussions/models/discussion.py
discussions/models/folder.py
discussions/models/message.py
discussions/models/recipient.py
discussions/templates/base.html
discussions/templates/discussions/_discussion.html
discussions/templates/discussions/base.html
discussions/templates/discussions/deleted.html
discussions/templates/discussions/detail.html
discussions/templates/discussions/form.html
discussions/templates/discussions/list.html
discussions/templates/discussions/read.html
discussions/templates/discussions/sent.html
discussions/templates/discussions/unread.html
discussions/templates/discussions/folder/create.html
discussions/templates/discussions/folder/detail.html
discussions/templates/discussions/folder/list.html
discussions/templates/discussions/folder/update.html
discussions/templatetags/__init__.py
discussions/templatetags/discussions_tags.py
discussions/tests/__init__.py
discussions/tests/settings.py
discussions/tests/test_fields.py
discussions/tests/test_forms.py
discussions/tests/test_models.py
discussions/tests/test_templatetags.py
discussions/tests/test_views.py
discussions/views/__init__.py
discussions/views/base.py
discussions/views/status.py
django_discussions.egg-info/PKG-INFO
django_discussions.egg-info/SOURCES.txt
django_discussions.egg-info/dependency_links.txt
django_discussions.egg-info/not-zip-safe
django_discussions.egg-info/top_level.txt