Metadata-Version: 1.1
Name: django-discussions
Version: 0.5.0
Summary: Messaging system for your users
Home-page: http://github.com/thoas/django-discussions
Author: Florent Messa
Author-email: florent.messa@gmail.com
License: UNKNOWN
Platform: UNKNOWN
Classifier: Environment :: Web Environment
Classifier: Intended Audience :: Developers
Classifier: License :: OSI Approved :: MIT License
Classifier: Operating System :: OS Independent
Classifier: Programming Language :: Python
Classifier: Programming Language :: Python :: 3
Classifier: Topic :: Utilities
